LICENSE.txt
README.rst
setup.cfg
setup.py
Jetski/Jetski.py
Jetski/__init__.py
Jetski.egg-info/PKG-INFO
Jetski.egg-info/SOURCES.txt
Jetski.egg-info/dependency_links.txt
Jetski.egg-info/top_level.txt